nimblebox/__init__.py
nimblebox/__main__.py
nimblebox/assets/exe.jinja
nimblebox/assets/ml.jinja
nimblebox/assets/readme.jinja
nimblebox/assets/user.jinja
nimblebox/auth.py
nimblebox/cli.py
nimblebox/framework/__init__.py
nimblebox/framework/autogen.py
nimblebox/framework/ml.py
nimblebox/framework/model_spec_pb2.py
nimblebox/framework/model_spec_pb2.pyi
nimblebox/framework/on_functions.py
nimblebox/framework/on_ml.py
nimblebox/framework/on_operators.py
nimblebox/framework/protos/model_spec.proto
nimblebox/hyperloop/.git
nimblebox/hyperloop/.gitignore
nimblebox/hyperloop/__init__.py
nimblebox/hyperloop/dag_pb2.py
nimblebox/hyperloop/dag_pb2.pyi
nimblebox/hyperloop/dag_pb2_grpc.py
nimblebox/hyperloop/dag_pb2_grpc.pyi
nimblebox/hyperloop/job_pb2.py
nimblebox/hyperloop/job_pb2.pyi
nimblebox/hyperloop/job_pb2_grpc.py
nimblebox/hyperloop/job_pb2_grpc.pyi
nimblebox/hyperloop/nbox_ws_pb2.py
nimblebox/hyperloop/nbox_ws_pb2.pyi
nimblebox/hyperloop/nbox_ws_pb2_grpc.py
nimblebox/hyperloop/nbox_ws_pb2_grpc.pyi
nimblebox/hyperloop/serve_pb2.py
nimblebox/hyperloop/serve_pb2.pyi
nimblebox/hyperloop/serve_pb2_grpc.py
nimblebox/hyperloop/serve_pb2_grpc.pyi
nimblebox/init.py
nimblebox/instance.py
nimblebox/jobs.py
nimblebox/lib/__init__.py
nimblebox/lib/arch.py
nimblebox/lib/aws.py
nimblebox/lib/comms.py
nimblebox/lib/demo.py
nimblebox/lib/exceptions.py
nimblebox/lib/nbx_instances.py
nimblebox/lib/shell.py
nimblebox/load.py
nimblebox/messages.py
nimblebox/model.py
nimblebox/nbxlib/tracer.py
nimblebox/network.py
nimblebox/operator.py
nimblebox/relics/__init__.py
nimblebox/relics/aws.py
nimblebox/relics/base.py
nimblebox/relics/local.py
nimblebox/relics/relic.py
nimblebox/sub_utils/__init__.py
nimblebox/sub_utils/latency.py
nimblebox/sub_utils/pub.crt
nimblebox/sub_utils/ssh.py
nimblebox/subway.py
nimblebox/utils.py
nimblebox/version.py
nimblebox-0.9.16.dist-info/LICENSE
nimblebox-0.9.16.dist-info/WHEEL
nimblebox-0.9.16.dist-info/METADATA
nimblebox-0.9.16.dist-info/RECORD
