Metadata-Version: 2.1
Name: nimblebox
Version: 0.9.16
Summary: ML Inference 🥶
Home-page: https://github.com/NimbleBoxAI/nbox
License: Apache-v2
Author: NBX Research
Author-email: research@nimblebox.ai
Requires-Python: >=3.7,<4.0
Classifier: License :: Other/Proprietary License
Classifier: Programming Language :: Python :: 3
Classifier: Programming Language :: Python :: 3.10
Classifier: Programming Language :: Python :: 3.7
Classifier: Programming Language :: Python :: 3.8
Classifier: Programming Language :: Python :: 3.9
Provides-Extra: serving
Requires-Dist: Jinja2 (==3.0.3)
Requires-Dist: dill (==0.3.4)
Requires-Dist: fastapi (>=0.78.0,<0.79.0); extra == "serving"
Requires-Dist: grpcio (==1.43.0)
Requires-Dist: mypy-protobuf (==3.2.0)
Requires-Dist: protobuf (==3.20.1)
Requires-Dist: python-json-logger (==2.0.2)
Requires-Dist: randomname (>=0.1.3,<0.2.0)
Requires-Dist: requests (>=2.25.1,<3.0.0)
Requires-Dist: tabulate (==0.8.9)
Requires-Dist: uvicorn (>=0.18.2,<0.19.0); extra == "serving"
Project-URL: Documentation, https://nimbleboxai.github.io/nbox/
Project-URL: Repository, https://github.com/NimbleBoxAI/nbox
